geopayment/__init__.py
geopayment/constants.py
geopayment/tests.py
geopayment/crypto/__init__.py
geopayment/crypto/crypto.py
geopayment/providers/__init__.py
geopayment/providers/utils.py
geopayment/providers/bog/__init__.py
geopayment/providers/bog/provider.py
geopayment/providers/bog/installment/__init__.py
geopayment/providers/bog/installment/form.py
geopayment/providers/credo/__init__.py
geopayment/providers/credo/provider.py
geopayment/providers/credo/installment/__init__.py
geopayment/providers/credo/installment/form.py
geopayment/providers/tbc/__init__.py
geopayment/providers/tbc/provider.py
geopayment-0.5.2.dist-info/METADATA
geopayment-0.5.2.dist-info/WHEEL
geopayment-0.5.2.dist-info/top_level.txt
geopayment-0.5.2.dist-info/RECORD
