Metadata-Version: 2.1
Name: geopayment
Version: 0.5.2
Summary: Python SDK for Georgian Payment Providers
Home-page: https://github.com/Lh4cKg/geopayment
Author: Lasha Gogua
Author-email: gogualasha@gmail.com
License: MIT
Keywords: python,geopayment,payments,sdk,merchant
Platform: OS Independent
Classifier: Environment :: Web Environment
Classifier: Intended Audience :: Developers
Classifier: License :: OSI Approved :: MIT License
Classifier: Operating System :: OS Independent
Classifier: Programming Language :: Python
Classifier: Topic :: Software Development :: Libraries :: Python Modules
Classifier: Topic :: Internet :: WWW/HTTP :: Dynamic Content
Classifier: Topic :: Internet :: WWW/HTTP :: Site Management
Classifier: Topic :: Software Development :: Libraries :: Application Frameworks
Classifier: Development Status :: 5 - Production/Stable
Classifier: Programming Language :: Python :: 3.7
Requires-Python: >=3.7
Requires-Dist: cryptography (>=3.3.2)
Requires-Dist: pyOpenSSL (>=21.0.0)
Requires-Dist: requests (>=2.26.0)
